chinamindata/__init__.py
chinamindata/c_min.py
chinamindata/change_time.py
chinamindata/china_list.py
chinamindata/china_min.py
chinamindata/china_min_close.py
chinamindata/china_min_open.py
chinamindata/example.py
chinamindata/min.py
chinamindata-0.1.2.dist-info/METADATA
chinamindata-0.1.2.dist-info/WHEEL
chinamindata-0.1.2.dist-info/top_level.txt
chinamindata-0.1.2.dist-info/RECORD
