Metadata-Version: 2.2
Name: chinamindata
Version: 0.1.2
Author: li
Author-email: 76@gmail.com
Platform: any
Requires-Dist: requests==2.32.3
Requires-Dist: pandas==2.2.3
Dynamic: author
Dynamic: author-email
Dynamic: platform
Dynamic: requires-dist
